raygun_django_middleware/__init__.py
raygun_django_middleware-1.0.9.dist-info/DESCRIPTION.rst
raygun_django_middleware-1.0.9.dist-info/METADATA
raygun_django_middleware-1.0.9.dist-info/RECORD
raygun_django_middleware-1.0.9.dist-info/WHEEL
raygun_django_middleware-1.0.9.dist-info/metadata.json
raygun_django_middleware-1.0.9.dist-info/top_level.txt
