Metadata-Version: 2.0
Name: raygun-django-middleware
Version: 1.0.9
Summary: Raygun Django Middleware
Home-page: https://github.com/mirusresearch/raygun-django-middleware
Author: Mirus Research
Author-email: frank@mirusresearch.com
License: MIT license, see LICENSE.txt
Platform: UNKNOWN
